[
  {
    "items": [
      {
        "item_id": 104,
        "name": "Salami",
        "variant_id": null,
        "variant_size": null,
        "price": 11,
        "quantity": 1
      }
    ],
    "paymentMethod": 3,
    "total": 0,
    "paid": 0,
    "change": 0,
    "tip": 0,
    "timestamp": "2025-09-12T11:54:49.413Z"
  },
  {
    "items": [
      {
        "item_id": 104,
        "name": "Salami",
        "variant_id": null,
        "variant_size": null,
        "price": 11,
        "quantity": 1
      }
    ],
    "paymentMethod": 3,
    "total": 0,
    "paid": 0,
    "change": 0,
    "tip": 0,
    "timestamp": "2025-09-12T11:56:26.866Z"
  },
  {
    "items": [
      {
        "item_id": 104,
        "name": "Salami",
        "variant_id": null,
        "variant_size": null,
        "price": 11,
        "quantity": 1
      }
    ],
    "paymentMethod": 3,
    "total": 0,
    "paid": 0,
    "change": 0,
    "tip": 0,
    "timestamp": "2025-09-12T12:02:44.252Z"
  }
]